psrecord/__init__.py
psrecord/__main__.py
psrecord/_version.py
psrecord/main.py
psrecord/tests/__init__.py
psrecord/tests/test_main.py
psrecord-1.4.dist-info/LICENSE
psrecord-1.4.dist-info/METADATA
psrecord-1.4.dist-info/WHEEL
psrecord-1.4.dist-info/entry_points.txt
psrecord-1.4.dist-info/top_level.txt
psrecord-1.4.dist-info/zip-safe
psrecord-1.4.dist-info/RECORD
