Metadata-Version: 2.1
Name: psrecord
Version: 1.4
Summary: Python package to record activity from processes
Author-email: Thomas Robitaille <thomas.robitaille@gmail.com>
License: Simplified BSD License
Project-URL: Homepage, https://github.com/astrofrog/psrecord
Classifier: Development Status :: 3 - Alpha
Classifier: Programming Language :: Python
Classifier: License :: OSI Approved :: BSD License
Provides: psrecord
License-File: LICENSE
Requires-Dist: psutil >=5.6
Provides-Extra: plot
Requires-Dist: matplotlib ; extra == 'plot'
Provides-Extra: test
Requires-Dist: pytest >=7.0 ; extra == 'test'
